Workbook

Sheet Sheet2
A3: Row Labels | B3: Total_Lab_Cost | C3: Total_SCA_Lab_Charge | D3: Total_Labor_Cost | E3: Total_Billed_Labor | F3: Gross_Margin | G3: Gross_Margin_Pct
A4: 23S-002 | D4: 1501 | E4: 2251.5 | F4: 750.5 | G4: 0.33333333
A5: 23S-004 | D5: 4446 | E5: 6669 | F5: 2223 | G5: 0.33333333
A6: 23S-006 | B6: 167 | C6: 569 | D6: 2913 | E6: 4369.5 | F6: 1858.5 | G6: 0.37632884
A7: 23S-010 | D7: 1216 | E7: 1824 | F7: 608 | G7: 0.33333333
A8: 23S-013 | D8: 1026 | E8: 1539 | F8: 513 | G8: 0.33333333
A9: 23S-019 | D9: 969 | E9: 1453.5 | F9: 484.5 | G9: 0.33333333
A10: 23S-024 | B10: 96 | C10: 306 | D10: 1235 | E10: 1852.5 | F10: 827.5 | G10: 0.38336808
A11: 23S-025 | D11: 342 | E11: 513 | F11: 171 | G11: 0.33333333
A12: 23S-026 | D12: 270 | E12: 405 | F12: 135 | G12: 0.33333333
A13: 23S-038 | D13: 1900 | E13: 2850 | F13: 950 | G13: 0.33333333
A14: 23S-042 | D14: 1387 | E14: 2080.5 | F14: 693.5 | G14: 0.33333333
A15: 23S-045 | B15: 336 | C15: 1138 | D15: 1387 | E15: 2080.5 | F15: 1495.5 | G15: 0.46465745
A16: 23S-052 | B16: 122 | C16: 369 | D16: 2299 | E16: 3448.5 | F16: 1396.5 | G16: 0.36581532
A17: 23S-058 | B17: 24 | C17: 96 | D17: 247 | E17: 370.5 | F17: 195.5 | G17: 0.41907824
A18: 23S-059 | B18: 182 | C18: 548 | D18: 3856 | E18: 5784 | F18: 2294 | G18: 0.3622868
A19: 23S-065 | D19: 646 | E19: 969 | F19: 323 | G19: 0.33333333
A20: 23S-072 | D20: 361 | E20: 541.5 | F20: 180.5 | G20: 0.33333333
A21: 23S-073 | B21: 134 | C21: 415 | F21: 281 | G21: 0.67710843
A22: 23S-074 | B22: 392 | C22: 1365 | F22: 973 | G22: 0.71282051
A23: 23S-075 | B23: 286 | C23: 895 | F23: 609 | G23: 0.68044693
A24: 23S-078 | B24: 402.5 | C24: 1506 | F24: 1103.5 | G24: 0.73273572
A25: 23S-087 | B25: 356 | C25: 1084 | F25: 728 | G25: 0.67158672
A26: 23S-103 | B26: 1489 | C26: 4490 | D26: 22238 | E26: 33357 | F26: 14120 | G26: 0.37308109
A27: 23S-106 | D27: 1121 | E27: 1681.5 | F27: 560.5 | G27: 0.33333333
A28: 23S-110 | B28: 316 | C28: 1061 | F28: 745 | G28: 0.70216777
A29: 23S-114 | B29: 552 | C29: 1672 | F29: 1120 | G29: 0.66985646
A30: 23S-138 | B30: 105 | C30: 415 | F30: 310 | G30: 0.74698795
A31: 24S-006 | B31: 140 | C31: 438 | D31: 2092.5 | E31: 3138.75 | F31: 1344.25 | G31: 0.37583001
A32: 24S-007 | B32: 288 | C32: 916 | F32: 628 | G32: 0.68558952
A33: 24S-022 | B33: 52 | C33: 196 | F33: 144 | G33: 0.73469388
A34: 24S-032 | B34: 64 | C34: 196 | D34: 1750 | E34: 2625 | F34: 1007 | G34: 0.35696562
A35: 24S-042 | B35: 460 | C35: 1418 | D35: 8423.5 | E35: 12635.25 | F35: 5169.75 | G35: 0.36786864
A36: 24S-055 | B36: 204 | C36: 638 | F36: 434 | G36: 0.68025078
A37: 24S-070 | B37: 152 | C37: 484 | D37: 3382 | E37: 5073 | F37: 2023 | G37: 0.36404535
A38: 24S-084 | B38: 20 | C38: 108 | D38: 2095.5 | E38: 3143.25 | F38: 1135.75 | G38: 0.34932718
A39: 24S-101 | B39: 186 | C39: 565 | D39: 3607 | E39: 5410.5 | F39: 2182.5 | G39: 0.3652414
A40: 24S-111 | B40: 293.5 | C40: 1009 | D40: 4198.5 | E40: 6297.75 | F40: 2814.75 | G40: 0.38522599
A41: 25S-010 | D41: 6344 | E41: 9516 | F41: 3172 | G41: 0.33333333
A42: (blank) | B42: 439 | C42: 1321 | D42: 36671 | E42: 55006.5 | F42: 19217.5 | G42: 0.34117438
A43: Grand Total | B43: 7258 | C43: 23218 | D43: 117924 | E43: 176886 | F43: 74922 | G43: 0.3744153

Sheet JOB LIST - SST
A1: SAI FILE NO | B1: BID | C1: PROJECT DESCRIPTION | D1: SCA SERVICE ID NO. | E1: SCA PROJECT ID NO.
A2: 25S-001 | B2: Q165 | C2: PO18 | D2: 94416 | E2: 141568
A3: 25S-002 | B3: X475 | C3: PO18 | D3: 94520
A4: 25S-003 | B4: K273 | C4: PO18 | D4: 94540 | E4: 141670
A5: 25S-004 | B5: Q189 | C5: PO18 | D5: 94758 | E5: 141770
A6: 25S-005 | B6: Q465 | C6: CTF | D6: 94367 | E6: 139246
A7: 25S-006 | B7: Q400 | C7: CTF
A8: 25S-007 | B8: R024 | C8: PO18
A9: 25S-008 | B9: Q189 | C9: PO18 | D9: 94587 | E9: 141701
A10: 25S-009 | B10: K384 | C10: PO18 | D10: 94618 | E10: 141715
A11: 25S-010 | B11: X107 | C11: PO18 | D11: 94758 | E11: 141770
A12: 25S-011 | B12: X030 | C12: PO18
A13: 25S-012 | B13: K138 | C13: PO18
A14: 25S-013 | B14: Q192 | C14: PO18
A15: 25S-014 | B15: Q420 | C15: CTF
A16: 25S-015 | B16: X131 | C16: PO18 | D16: 94778 | E16: 141789
A17: 25S-016 | B17: X005 | C17: CTF
A18: 25S-017 | B18: K209 | C18: CTF
A19: 25S-018 | B19: K495 | C19: CTF | D19: 95250
A20: 25S-019 | B20: Q400 | C20: CTF
A21: 25S-020 | B21: M183 | C21: CIP | D21: 50159 | E21: 77931
A22: 25S-021 | B22: Q465 | C22: CTF Room Conv
A23: 25S-022 | B23: Q520
A24: 25S-023 | B24: X101 | C24: CTF Path of Travel | D24: 97179 | E24: 138996
A25: 25S-024 | B25: M017 | C25: CIP
A26: 25S-025 | B26: Q465 | C26: CTF Room Conv | D26: 97388 | E26: 141485
A27: 25S-026 | B27: Q465 | C27: CTF Room Conv | D27: 97386 | E27: 141478
A28: 25S-027 | B28: X149 | C28: CTF Path of Travel | D28: 94661 | E28: 138998
A29: 25S-028 | B29: Q025 | C29: CTF Room Conv | D29: 97450 | E29: 141484
A30: 25S-029 | B30: K019 | C30: CIP
A31: 25S-030 | B31: M030 | C31: CTF | D31: 97448 | E31: 142187
A32: 25S-031 | B32: M625 | C32: CTF Room Conv | D32: 97169 | E32: 141386
A33: 25S-032 | B33: K324 | C33: CTR Room Conv | D33: 97724 | E33: 130667
A34: 25S-033 | B34: R001 | C34: PO18
A35: 25S-034 | B35: M435 | C35: PO18 | D35: 97818 | E35: 144881
A36: 25S-035 | B36: R440 | C36: PO18
A37: 25S-036 | B37: Q460 | C37: CTF Room Conv | D37: 97613 | E37: 141636
A38: 25S-037 | B38: Q460 | C38: CTF Path of Travel | D38: 97650 | E38: 141634
A39: 25S-038 | B39: K420 | C39: RESO LAP | D39: 97776 | E39: 139888
A40: 25S-039 | B40: M166 | C40: RESO LAP | D40: 97706 | E40: 139989
A41: 25S-040 | B41: M001 | C41: CIP
A42: 25S-041 | B42: K099 | C42: PO18 | D42: 97786 | E42: 144864
A43: 25S-042 | B43: M165 | C43: PO18 | D43: 97816 | E43: 144879
A44: 25S-043 | B44: Q214 | C44: PO18
A45: 25S-044 | B45: M096 | C45: PO18 | D45: 97540 | E45: 143655
A46: 25S-045 | B46: X149 | C46: PO18
A47: 24S-001 | B47: R060
A48: 24S-002 | B48: M440 | C48: PO18 | D48: 90375 | E48: 138341
A49: 24S-003 | B49: M187 | C49: PO18 | D49: 90610 | E49: 138462
A50: 24S-004 | B50: K050 | C50: CTF | D50: 90587 | E50: 138375
A51: 24S-005 | B51: R435 | C51: CIP | D51: 90083 | E51: 130440
A52: 24S-006 | B52: M192 | C52: PO18 | D52: 90701 | E52: 138488
A53: 24S-007 | B53: K261 | C53: CIP/CTF | D53: 90763 | E53: P026332
A54: 24S-008 | B54: R002 | C54: PO18 | D54: 91184 | E54: 138746
A55: 24S-009 | B55: Q460 | C55: PO18 | D55: 90480 | E55: 138411
A56: 24S-010 | B56: Q021 | C56: PO18
A57: 24S-011 | B57: R022 | C57: CIP | D57: 82742 | E57: D019615
A58: 24S-012 | B58: K017 | C58: PO18 | D58: 90624 | E58: 138470
A59: 24S-013 | B59: Q460 | C59: PO18 | D59: 90784 | E59: 138614
A60: 24S-014 | B60: K160 | C60: PO18 | D60: 90892 | E60: 138638
A61: 24S-015 | B61: Q165 | C61: PO18 | D61: 88306 | E61: 135518
A62: 24S-016 | B62: K232 | C62: CTF | D62: 89776 | E62: 126994
A63: 24S-017 | B63: K232 | C63: CTF | D63: 89766 | E63: 126993
A64: 24S-018 | B64: K232 | C64: CTF | D64: 89768 | E64: 126995
A65: 24S-019 | B65: Q225 | C65: CTF | D65: 89359 | E65: 133978
A66: 24S-020 | B66: Q225 | C66: CTF | D66: 89963 | E66: 133979
A67: 24S-021 | B67: R075 | C67: PO18 | D67: 91329 | E67: 138795
A68: 24S-022 | B68: M028 | C68: PO18 | D68: 91258 | E68: 138763
A69: 24S-023 | B69: M163 | C69: PO18 | D69: 91391 | E69: 138821
... A74: 24S-028 | B74: Q141 | C74: PO18 | D74: 91394 | E74: 138818
A75: 24S-029 | B75: Q442 | C75: PO18
A76: 24S-030 | B76: K600 | C76: PO18 | D76: 91760 | E76: 139066
A77: 24S-031 | B77: Q023 | C77: PO18 | D77: 91807 | E77: 139091
A78: 24S-032 | B78: Q442 | C78: PO18 | D78: 91854 | E78: 139110
A79: 24S-033 | B79: R013 | C79: CTF | D79: 91809 | E79: 138991
A80: 24S-034 | B80: R013 | C80: CTF | D80: 91836 | E80: 138990
A81: 24S-035 | B81: Q037 | C81: CTF | D81: 91801 | E81: 138692
A82: 24S-036 | B82: Q037 | C82: CTF | D82: 91803 | E82: 138669
A83: 24S-037 | B83: Q442 | C83: PO18 | D83: 91832 | E83: 139100
A84: 24S-038 | B84: K104 | C84: PO18 | D84: 91880 | E84: 139122
A85: 24S-039 | B85: X049 | C85: PO18
A86: 24S-040 | B86: Q231 | C86: Special Program
A87: 24S-041 | B87: Q203 | C87: PO18
A88: 24S-042 | B88: M064 | C88: PO18
A89: 24S-043 | B89: R008 | C89: PO18 | D89: 92211 | E89: 139298
A90: 24S-044 | B90: X074 | C90: CIP | D90: 91863 | E90: 137129
A91: 24S-045 | B91: K316 | C91: CTF | D91: 91953 | E91: 135593
A92: 24S-046 | B92: R040 | C92: PO18 | D92: 89229 | E92: 136104
A93: 24S-047 | B93: Q024 | C93: PO18 | D93: 91978 | E93: 139172
A94: 24S-048 | B94: M050 | C94: PO18 | D94: 91997 | E94: 139182
A95: 24S-049 | B95: M115 | C95: CTF | D95: 92097 | E95: 138655
A96: 24S-050 | B96: R455 | C96: PO18
A97: 24S-051 | B97: Q023 | D97: 92210 | E97: 139296
A98: 24S-052 | B98: Q438 | C98: PO18 | D98: 92209 | E98: 139297
A99: 24S-053 | B99: M152 | C99: PO18 | D99: 92223 | E99: 139302
A100: 24S-054 | B100: K162 | C100: PO18 | D100: 92352 | E100: 139348
A101: 24S-055 | B101: X065 | C101: PO18 | D101: 92350 | E101: 139346
A102: 24S-056 | B102: Q480 | C102: Special Program | D102: 92299 | E102: 134515
A103: 24S-057 | B103: X005 | C103: CTF | D103: 92195 | E103: 138646
A104: 24S-058 | B104: X149 | C104: CTF | D104: 92199 | E104: 138999
...

Sheet CIP-REOCC
A1: JOBID | B1: BID | C1: START_DATE | D1: END_DATE | E1: LOCATION | F1: AMT_OF_ACM
A2: 22S-067 | B2: R005 | C2: 45141 | D2: 45142 | E2: 1-3 FL HALLWAY | F2: 90
A3: 22S-067 | B3: R005 | C3: 45497 | D3: 45499 | E3: FL 1-3 EXT FAÇADE EAST | F3: 45
A4: 22S-067 | B4: R005 | C4: 45497 | D4: 45499 | E4: 3RD FL EXT FAÇADE | F4: 90
A5: 23S-006 | B5: Q205 | C5: 45058 | D5: 45060 | E5: RM 329, 331, 333 | F5: 1154
A6: 23S-006 | B6: Q205 | C6: 45094 | D6: 45094 | E6: RM 322, 222, 122 | F6: 670
A7: 23S-045 | B7: M115 | C7: 45128 | D7: 7/23/023 | E7: 1st Fl Kitchen Staff Bath, Stair 6, 8 | F7: 150
A8: 23S-045 | B8: M115 | C8: 45135 | D8: 45137 | E8: 4th Fl Stair #6, 8, 5th Fl Stair #2,4 | F8: 142
A9: 23S-045 | B9: M115 | C9: 45142 | D9: 45144 | E9: Hall by 502, 503, 504. 509, 511, Boy's Bath | F9: 100
A10: 23S-045 | B10: M115 | C10: 45149 | D10: 45151 | E10: Flrs 1-3.5 | F10: 130
A11: 23S-045 | B11: M115 | C11: 45205 | D11: 45206 | E11: 513B | F11: 600
A12: 23S-052 | B12: X107 | C12: 45219 | D12: 45220 | E12: RM 123, 401A | F12: 1206
A13: 23S-058 | B13: X101 | C13: 45276 | D13: 45277 | E13: RM 103, 107 | F13: 90
A14: 23S-059 | B14: X085 | C14: 45155 | D14: 45156 | E14: RM 106, 108 | F14: 1234
A15: 23S-059 | B15: X085 | C15: 45159 | D15: 45162 | E15: B3, B4/B6, B5, B7, B8, B10 | F15: 3400
A16: 23S-073 | B16: Q022 | C16: 45597 | D16: 45598 | E16: RM 209 | F16: 1154
A17: 23S-073 | B17: Q022 | C17: 45604 | D17: 45605 | E17: FL 1-3, LANDING OF STAIR B | F17: 670
A18: 23S-074 | B18: R053 | C18: 45219 | D18: 45220 | E18: RM 201, 203 | F18: 1488
A19: 23S-074 | B19: R053 | C19: 45226 | D19: 45227 | E19: RM 202, 204 | F19: 1520
... A29: 23S-075 | B29: K335 | C29: 45475 | D29: 45476 | E29: 3rd Floor – Room, 303 | F29: 740
A30: 23S-078 | B30: M169 | C30: 45175 | D30: 45175 | E30: BULK
A31: 23S-078 | B31: M169 | C31: 45458 | D31: 45459 | E31: ROOF B - PLAYDECK | F31: 1220
A32: 23S-078 | B32: M169 | C32: 45514 | D32: 45514 | E32: GROUND - E SIDE | F32: 9
A33: 23S-078 | B33: M169 | C33: 45556 | D33: 45556 | E33: N FAÇADE RM 417 | F33: 1
A34: 23S-078 | B34: M169 | C34: 45625 | D34: 45627 | E34: GRND FL W SIDE ENT | F34: 740
A35: 23S-078 | B35: M169 | C35: 45684 | D35: 45686 | F35: 1
A36: 23S-078 | B36: M169 | C36: 45686 | D36: 45687 | F36: 1
A37: 23S-078 | B37: M169 | C37: 45691 | D37: 45691 | F37: 1
A38: 23S-078 | B38: M169 | C38: 45701 | D38: 45702 | F38: 1
A39: 23S-078 | B39: M169 | C39: 45712 | D39: 45712 | F39: 1
A40: 23S-078 | B40: M169 | C40: 45719 | D40: 45719 | F40: 1
A41: 23S-078 | B41: M169 | C41: 45733 | D41: 45733 | F41: 1
A42: 23S-078 | B42: M169 | C42: 45771 | D42: 45771 | F42: 1
A43: 23S-078 | B43: M169 | C43: 45726 | D43: 45726 | F43: 1
A44: 23S-078 | B44: M169 | C44: 45772 | D44: 45774 | E44: VESTIBULE 329, 330 | F44: 260
A45: 23S-087 | B45: K110 | C45: 45233 | D45: 45234 | E45: 2nd Fl Corridor | F45: 317
A46: 23S-087 | B46: K110 | C46: 45233 | D46: 45234 | E46: 3rd Fl Rm 303 | F46: 630
A47: 23S-087 | B47: K110 | C47: 45240 | D47: 45241 | E47: 3rd Fl Rm 301, 302 | F47: 1230
A48: 23S-087 | B48: K110 | C48: 45247 | D48: 45248 | E48: 3rd Fl Rm 305, 306 | F48: 1254
A49: 23S-087 | B49: K110 | C49: 45252 | D49: 45255 | E49: 2nd Fl Corridor, Landings, A, C, G, E & Principal's Office | F49: 2448
A50: 23S-087 | B50: K110 | C50: 45261 | D50: 45262 | E50: 3rd Fl Asst Principal Office, Rm 312 | F50: 960
A51: 23S-103 | B51: Q165 | C51: 45541 | D51: 45542 | E51: 3rd Floor – Room 325 & 327 | F51: 1152
A52: 23S-103 | B52: Q165 | C52: 45548 | D52: 45549 | E52: 3rd Floor – Room 333 | F52: 768
A53: 23S-103 | B53: Q165 | C53: 45569 | D53: 45570 | E53: 3rd Floor – Room 332 & 334 | F53: 1000
A54: 23S-103 | B54: Q165 | C54: 45576 | D54: 45577 | E54: 3rd Floor – Room 301 | F54: 796
A55: 23S-103 | B55: Q165 | C55: 45583 | D55: 45584 | E55: 3rd Floor – Room 320 | F55: 720
... A118: 24S-101 | B118: Q188 | C118: 45695 | D118: 45696 | E118: RM 114, 204 | F118: 1040

Sheet LABS
A1: JOBID | B1: BID | C1: COUNT | D1: BATCH NO | E1: SAMPLE TYPE | F1: Code | G1: DATE COLLECTED | H1: TECHNICIAN | I1: LOCATION | J1: Facility | K1: LAB COST | L1: SCA_Lab_Charge
A2: 22S-051 | B2: K600 | C2: 15 | D2: 12-129-001-PL | E2: PLM | F2: L04 | G2: 44915 | H2: DIMITRI | I2: RM 229, 231 | J2: LTS | K2: =INDEX('LAB PRICES'!$C$2:$F$12, MATCH(tblLabs[[#This Row],[Code]], 'LAB PRICES'!$A$2:$A$12, 0), MATCH(tblLabs[[#This Row],[Facility]], 'LAB PRICES'!$C$1:$F$1, 0)) -> 16 | L2: =_xlfn.XLOOKUP( tblLabs[[#This Row],[Code]], 'LAB PRICES'!$A$2:$A$12, 'LAB PRICES'!$G$2:$G$12 ) -> 23
A3: 22S-051 | B3: K600 | C3: 39 | D3: 12-129-001-PN | E3: PLM-NOB | F3: L05 | G3: 44915 | H3: DIMITRI | I3: RM 229, 231 | J3: LTS | K3: =INDEX('LAB PRICES'!$C$2:$F$12, MATCH(tblLabs[[#This Row],[Code]], 'LAB PRICES'!$A$2:$A$12, 0), MATCH(tblLabs[[#This Row],[Facility]], 'LAB PRICES'!$C$1:$F$1, 0)) -> 6 | L3: =_xlfn.XLOOKUP( tblLabs[[#This Row],[Code]], 'LAB PRICES'!$A$2:$A$12, 'LAB PRICES'!$G$2:$G$12 ) -> 40
A4: 22S-051 | B4: K600 | C4: 39 | D4: 12-129-001-TN | E4: TEM-NOB | F4: L06 | G4: 44915 | H4: DIMITRI | I4: RM 229, 231 | J4: LTS | K4: =INDEX('LAB PRICES'!$C$2:$F$12, MATCH(tblLabs[[#This Row],[Code]], 'LAB PRICES'!$A$2:$A$12, 0), MATCH(tblLabs[[#This Row],[Facility]], 'LAB PRICES'!$C$1:$F$1, 0)) -> 26 | L4: =_xlfn.XLOOKUP( tblLabs[[#This Row],[Code]], 'LAB PRICES'!$A$2:$A$12, 'LAB PRICES'!$G$2:$G$12 ) -> 70
A5: 22S-051 | B5: K600 | C5: 15 | D5: 215550-0 | E5: PCB | F5: L10 | G5: 44915 | H5: DIMITRI | I5: RM 229, 231 | J5: KAM | K5: =INDEX('LAB PRICES'!$C$2:$F$12, MATCH(tblLabs[[#This Row],[Code]], 'LAB PRICES'!$A$2:$A$12, 0), MATCH(tblLabs[[#This Row],[Facility]], 'LAB PRICES'!$C$1:$F$1, 0)) -> 80 | L5: =_xlfn.XLOOKUP( tblLabs[[#This Row],[Code]], 'LAB PRICES'!$A$2:$A$12, 'LAB PRICES'!$G$2:$G$12 ) -> 140
A6: 22S-051 | B6: K600 | C6: 12 | D6: 23-06-818 | E6: PCM | F6: L01 | G6: 45106 | H6: Chi Fei Hung | I6: RM 231 | J6: LTS | K6: =INDEX('LAB PRICES'!$C$2:$F$12, MATCH(tblLabs[[#This Row],[Code]], 'LAB PRICES'!$A$2:$A$12, 0), MATCH(tblLabs[[#This Row],[Facility]], 'LAB PRICES'!$C$1:$F$1, 0)) -> 6 | L6: =_xlfn.XLOOKUP( tblLabs[[#This Row],[Code]], 'LAB PRICES'!$A$2:$A$12, 'LAB PRICES'!$G$2:$G$12 ) -> 23
A7: 22S-051 | B7: K600 | C7: 5 | D7: 23-07-019 | E7: TEM | F7: L03 | G7: 45110 | H7: Chi Fei Hung | I7: RM 231 | J7: LTS | K7: =INDEX('LAB PRICES'!$C$2:$F$12, MATCH(tblLabs[[#This Row],[Code]], 'LAB PRICES'!$A$2:$A$12, 0), MATCH(tblLabs[[#This Row],[Facility]], 'LAB PRICES'!$C$1:$F$1, 0)) -> 40 | L7: =_xlfn.XLOOKUP( tblLabs[[#This Row],[Code]], 'LAB PRICES'!$A$2:$A$12, 'LAB PRICES'!$G$2:$G$12 ) -> 100
A8: 22S-051 | B8: K600 | C8: 8 | D8: 23-07-022 | E8: PCM | F8: L01 | G8: 45107 | H8: Chi Fei Hung | I8: RM 231 | J8: LTS | K8: =INDEX('LAB PRICES'!$C$2:$F$12, MATCH(tblLabs[[#This Row],[Code]], 'LAB PRICES'!$A$2:$A$12, 0), MATCH(tblLabs[[#This Row],[Facility]], 'LAB PRICES'!$C$1:$F$1, 0)) -> 6 | L8: =_xlfn.XLOOKUP( tblLabs[[#This Row],[Code]], 'LAB PRICES'!$A$2:$A$12, 'LAB PRICES'!$G$2:$G$12 ) -> 23
A9: 22S-051 | B9: K600 | C9: 12 | D9: 23-07-023 | E9: PCM | F9: L01 | G9: 45107 | H9: Chi Fei Hung | I9: RM 231 | J9: LTS | K9: =INDEX('LAB PRICES'!$C$2:$F$12, MATCH(tblLabs[[#This Row],[Code]], 'LAB PRICES'!$A$2:$A$12, 0), MATCH(tblLabs[[#This Row],[Facility]], 'LAB PRICES'!$C$1:$F$1, 0)) -> 6 | L9: =_xlfn.XLOOKUP( tblLabs[[#This Row],[Code]], 'LAB PRICES'!$A$2:$A$12, 'LAB PRICES'!$G$2:$G$12 ) -> 23
A10: 22S-051 | B10: K600 | C10: 34 | D10: 23-07-057 | E10: PCM | F10: L01 | G10: 45108 | H10: Chi Fei Hung | I10: RM 231 | J10: LTS | K10: =INDEX('LAB PRICES'!$C$2:$F$12, MATCH(tblLabs[[#This Row],[Code]], 'LAB PRICES'!$A$2:$A$12, 0), MATCH(tblLabs[[#This Row],[Facility]], 'LAB PRICES'!$C$1:$F$1, 0)) -> 6 | L10: =_xlfn.XLOOKUP( tblLabs[[#This Row],[Code]], 'LAB PRICES'!$A$2:$A$12, 'LAB PRICES'!$G$2:$G$12 ) -> 23
A11: 22S-051 | B11: K600 | C11: 12 | D11: 23-07-094 | E11: FINALS | F11: L02 | G11: 45110 | H11: Chi Fei Hung | I11: RM 231 | J11: LTS | K11: =INDEX('LAB PRICES'!$C$2:$F$12, MATCH(tblLabs[[#This Row],[Code]], 'LAB PRICES'!$A$2:$A$12, 0), MATCH(tblLabs[[#This Row],[Facility]], 'LAB PRICES'!$C$1:$F$1, 0)) -> 6 | L11: =_xlfn.XLOOKUP( tblLabs[[#This Row],[Code]], 'LAB PRICES'!$A$2:$A$12, 'LAB PRICES'!$G$2:$G$12 ) -> 27
A12: 22S-051 | B12: K600 | C12: 7 | D12: 231210-4 | E12: DAF | F12: L02 | G12: 45270 | H12: Tatiana Ciobanu | I12: BTN 356 & 358, 256 & 258 | J12: ALLAB | K12: =INDEX('LAB PRICES'!$C$2:$F$12, MATCH(tblLabs[[#This Row],[Code]], 'LAB PRICES'!$A$2:$A$12, 0), MATCH(tblLabs[[#This Row],[Facility]], 'LAB PRICES'!$C$1:$F$1, 0)) -> 5 | L12: =_xlfn.XLOOKUP( tblLabs[[#This Row],[Code]], 'LAB PRICES'!$A$2:$A$12, 'LAB PRICES'!$G$2:$G$12 ) -> 27
A13: 22S-051 | B13: K600 | C13: 14 | D13: 24-02-077 | E13: DAF | F13: L02 | G13: 45325 | H13: Joi Fei Hung | I13: RM 231, 229, 131 | J13: LTS | K13: =INDEX('LAB PRICES'!$C$2:$F$12, MATCH(tblLabs[[#This Row],[Code]], 'LAB PRICES'!$A$2:$A$12, 0), MATCH(tblLabs[[#This Row],[Facility]], 'LAB PRICES'!$C$1:$F$1, 0)) -> 6 | L13: =_xlfn.XLOOKUP( tblLabs[[#This Row],[Code]], 'LAB PRICES'!$A$2:$A$12, 'LAB PRICES'!$G$2:$G$12 ) -> 27
... A84: 23S-052 | B84: X107 | C84: 12 | D84: 23-10-494 | E84: PCM | F84: L01 | G84: 45219 | H84: Joi Fei Hung | I84: RM 401A | J84: LTS | K84: =INDEX('LAB PRICES'!$C$2:$F$12, MATCH(tblLabs[[#This Row],[Code]], 'LAB PRICES'!$A$2:$A$12, 0), MATCH(tblLabs[[#This Row],[Facility]], 'LAB PRICES'!$C$1:$F$1, 0)) -> 6 | L84: =_xlfn.XLOOKUP( tblLabs[[#This Row],[Code]], 'LAB PRICES'!$A$2:$A$12, 'LAB PRICES'!$G$2:$G$12 ) -> 23
A85: 23S-052 | B85: X107 | D85: 23-10-495 | E85: PCM | F85: L01 | G85: 45219 | H85: Ricardo Vilchez | I85: RM 123 | J85: LTS | K85: =INDEX('LAB PRICES'!$C$2:$F$12, MATCH(tblLabs[[#This Row],[Code]], 'LAB PRICES'!$A$2:$A$12, 0), MATCH(tblLabs[[#This Row],[Facility]], 'LAB PRICES'!$C$1:$F$1, 0)) -> 6 | L85: =_xlfn.XLOOKUP( tblLabs[[#This Row],[Code]], 'LAB PRICES'!$A$2:$A$12, 'LAB PRICES'!$G$2:$G$12 ) -> 23
A86: 23S-052 | B86: X107 | D86: 23-10-496 | E86: PCM | F86: L01 | G86: 45219 | H86: Joi Fei Hung | I86: RM 401A | J86: LTS | K86: =INDEX('LAB PRICES'!$C$2:$F$12, MATCH(tblLabs[[#This Row],[Code]], 'LAB PRICES'!$A$2:$A$12, 0), MATCH(tblLabs[[#This Row],[Facility]], 'LAB PRICES'!$C$1:$F$1, 0)) -> 6 | L86: =_xlfn.XLOOKUP( tblLabs[[#This Row],[Code]], 'LAB PRICES'!$A$2:$A$12, 'LAB PRICES'!$G$2:$G$12 ) -> 23
A87: 23S-052 | B87: X107 | D87: 23-10-497 | E87: PCM | F87: L01 | G87: 45219 | H87: Ricardo Vilchez | I87: RM 123 | J87: LTS | K87: =INDEX('LAB PRICES'!$C$2:$F$12, MATCH(tblLabs[[#This Row],[Code]], 'LAB PRICES'!$A$2:$A$12, 0), MATCH(tblLabs[[#This Row],[Facility]], 'LAB PRICES'!$C$1:$F$1, 0)) -> 6 | L87: =_xlfn.XLOOKUP( tblLabs[[#This Row],[Code]], 'LAB PRICES'!$A$2:$A$12, 'LAB PRICES'!$G$2:$G$12 ) -> 23
A88: 23S-058 | B88: X101 | C88: 12 | D88: 23-12-456 | E88: PCM | F88: L01 | G88: 45275 | H88: Cornel Albu | I88: RM 103A, 107 | J88: LTS | K88: =INDEX('LAB PRICES'!$C$2:$F$12, MATCH(tblLabs[[#This Row],[Code]], 'LAB PRICES'!$A$2:$A$12, 0), MATCH(tblLabs[[#This Row],[Facility]], 'LAB PRICES'!$C$1:$F$1, 0)) -> 6 | L88: =_xlfn.XLOOKUP( tblLabs[[#This Row],[Code]], 'LAB PRICES'!$A$2:$A$12, 'LAB PRICES'!$G$2:$G$12 ) -> 23
A89: 23S-058 | B89: X101 | C89: 11 | D89: 23-12-533 | E89: PCM | F89: L01 | G89: 45276 | H89: Chi Fei Hung | I89: RM 103A, 107 | J89: LTS | K89: =INDEX('LAB PRICES'!$C$2:$F$12, MATCH(tblLabs[[#This Row],[Code]], 'LAB PRICES'!$A$2:$A$12, 0), MATCH(tblLabs[[#This Row],[Facility]], 'LAB PRICES'!$C$1:$F$1, 0)) -> 6 | L89: =_xlfn.XLOOKUP( tblLabs[[#This Row],[Code]], 'LAB PRICES'!$A$2:$A$12, 'LAB PRICES'!$G$2:$G$12 ) -> 23
A90: 23S-058 | B90: X101 | C90: 7 | D90: 23-12-534 | E90: PCM | F90: L01 | G90: 45276 | H90: Chi Fei Hung | I90: RM 103A, 107 | J90: LTS | K90: =INDEX('LAB PRICES'!$C$2:$F$12, MATCH(tblLabs[[#This Row],[Code]], 'LAB PRICES'!$A$2:$A$12, 0), MATCH(tblLabs[[#This Row],[Facility]], 'LAB PRICES'!$C$1:$F$1, 0)) -> 6 | L90: =_xlfn.XLOOKUP( tblLabs[[#This Row],[Code]], 'LAB PRICES'!$A$2:$A$12, 'LAB PRICES'!$G$2:$G$12 ) -> 23
A91: 23S-058 | B91: X101 | C91: 17 | D91: 23-12-535 | E91: FINALS | F91: L02 | G91: 45277 | H91: Chi Fei Hung | I91: RM 103A, 107 | J91: LTS | K91: =INDEX('LAB PRICES'!$C$2:$F$12, MATCH(tblLabs[[#This Row],[Code]], 'LAB PRICES'!$A$2:$A$12, 0), MATCH(tblLabs[[#This Row],[Facility]], 'LAB PRICES'!$C$1:$F$1, 0)) -> 6 | L91: =_xlfn.XLOOKUP( tblLabs[[#This Row],[Code]], 'LAB PRICES'!$A$2:$A$12, 'LAB PRICES'!$G$2:$G$12 ) -> 27
A92: 23S-059 | B92: X085 | C92: 9 | D92: 23-07-198-PL | E92: PLM | F92: L04 | G92: 45131 | H92: Ricardo Vilchez | I92: B4-B7, B10, 110, 111, 106 &108 | J92: LTS | K92: =INDEX('LAB PRICES'!$C$2:$F$12, MATCH(tblLabs[[#This Row],[Code]], 'LAB PRICES'!$A$2:$A$12, 0), MATCH(tblLabs[[#This Row],[Facility]], 'LAB PRICES'!$C$1:$F$1, 0)) -> 16 | L92: =_xlfn.XLOOKUP( tblLabs[[#This Row],[Code]], 'LAB PRICES'!$A$2:$A$12, 'LAB PRICES'!$G$2:$G$12 ) -> 23
A93: 23S-059 | B93: X085 | C93: 9 | D93: 23-07-198-PN | E93: PLM-NOB | F93: L05 | G93: 45131 | H93: Ricardo Vilchez | I93: B4-B7, B10, 110, 111, 106 &108 | J93: LTS | K93: =INDEX('LAB PRICES'!$C$2:$F$12, MATCH(tblLabs[[#This Row],[Code]], 'LAB PRICES'!$A$2:$A$12, 0), MATCH(tblLabs[[#This Row],[Facility]], 'LAB PRICES'!$C$1:$F$1, 0)) -> 6 | L93: =_xlfn.XLOOKUP( tblLabs[[#This Row],[Code]], 'LAB PRICES'!$A$2:$A$12, 'LAB PRICES'!$G$2:$G$12 ) -> 40
A94: 23S-059 | B94: X085 | C94: 9 | D94: 23-07-198-TN | E94: TEM-NOB | F94: L06 | G94: 45131 | H94: Ricardo Vilchez | I94: B4-B7, B10, 110, 111, 106 &108 | J94: LTS | K94: =INDEX('LAB PRICES'!$C$2:$F$12, MATCH(tblLabs[[#This Row],[Code]], 'LAB PRICES'!$A$2:$A$12, 0), MATCH(tblLabs[[#This Row],[Facility]], 'LAB PRICES'!$C$1:$F$1, 0)) -> 26 | L94: =_xlfn.XLOOKUP( tblLabs[[#This Row],[Code]], 'LAB PRICES'!$A$2:$A$12, 'LAB PRICES'!$G$2:$G$12 ) -> 70
A95: 23S-059 | B95: X085 | C95: 12 | D95: 23-08-1068 | E95: FINALS | F95: L02 | G95: 45161 | H95: Chi Fei Hung | I95: B10, B8, B7, B6, B4, B5, B3 | J95: LTS | K95: =INDEX('LAB PRICES'!$C$2:$F$12, MATCH(tblLabs[[#This Row],[Code]], 'LAB PRICES'!$A$2:$A$12, 0), MATCH(tblLabs[[#This Row],[Facility]], 'LAB PRICES'!$C$1:$F$1, 0)) -> 6 | L95: =_xlfn.XLOOKUP( tblLabs[[#This Row],[Code]], 'LAB PRICES'!$A$2:$A$12, 'LAB PRICES'!$G$2:$G$12 ) -> 27
A96: 23S-059 | B96: X085 | C96: 27 | D96: 23-08-1069 | E96: PCM | F96: L01 | G96: 45161 | H96: Chi Fei Hung | I96: B10, B8, B7, B6, B4, B5, B3 | J96: LTS | K96: =INDEX('LAB PRICES'!$C$2:$F$12, MATCH(tblLabs[[#This Row],[Code]], 'LAB PRICES'!$A$2:$A$12, 0), MATCH(tblLabs[[#This Row],[Facility]], 'LAB PRICES'!$C$1:$F$1, 0)) -> 6 | L96: =_xlfn.XLOOKUP( tblLabs[[#This Row],[Code]], 'LAB PRICES'!$A$2:$A$12, 'LAB PRICES'!$G$2:$G$12 ) -> 23
A97: 23S-059 | B97: X085 | C97: 5 | D97: 23-08-172 | E97: TEM | F97: L03 | G97: 45156 | H97: Joi Fei Hung | I97: RM 106, 108 | J97: LTS | K97: =INDEX('LAB PRICES'!$C$2:$F$12, MATCH(tblLabs[[#This Row],[Code]], 'LAB PRICES'!$A$2:$A$12, 0), MATCH(tblLabs[[#This Row],[Facility]], 'LAB PRICES'!$C$1:$F$1, 0)) -> 40 | L97: =_xlfn.XLOOKUP( tblLabs[[#This Row],[Code]], 'LAB PRICES'!$A$2:$A$12, 'LAB PRICES'!$G$2:$G$12 ) -> 100
A98: 23S-059 | B98: X085 | C98: 5 | D98: 23-08-218 | E98: TEM | F98: L03 | G98: 45161 | H98: Chi Fei Hung | I98: B10, B8, B7, B6, B4, B5, B3 | J98: LTS | K98: =INDEX('LAB PRICES'!$C$2:$F$12, MATCH(tblLabs[[#This Row],[Code]], 'LAB PRICES'!$A$2:$A$12, 0), MATCH(tblLabs[[#This Row],[Facility]], 'LAB PRICES'!$C$1:$F$1, 0)) -> 40 | L98: =_xlfn.XLOOKUP( tblLabs[[#This Row],[Code]], 'LAB PRICES'!$A$2:$A$12, 'LAB PRICES'!$G$2:$G$12 ) -> 100
A99: 23S-059 | B99: X085 | C99: 12 | D99: 23-08-664 | E99: PCM | F99: L01 | G99: 45153 | H99: Joi Fei Hung | I99: RM 106, 108 | J99: LTS | K99: =INDEX('LAB PRICES'!$C$2:$F$12, MATCH(tblLabs[[#This Row],[Code]], 'LAB PRICES'!$A$2:$A$12, 0), MATCH(tblLabs[[#This Row],[Facility]], 'LAB PRICES'!$C$1:$F$1, 0)) -> 6 | L99: =_xlfn.XLOOKUP( tblLabs[[#This Row],[Code]], 'LAB PRICES'!$A$2:$A$12, 'LAB PRICES'!$G$2:$G$12 ) -> 23
... A137: 23S-074 | B137: R053 | C137: 12 | D137: 231209-1 | E137: FINALS | F137: L02 | G137: 45269 | H137: Igor Groysman | I137: RM 205, 235 | J137: ALLAB | K137: =INDEX('LAB PRICES'!$C$2:$F$12, MATCH(tblLabs[[#This Row],[Code]], 'LAB PRICES'!$A$2:$A$12, 0), MATCH(tblLabs[[#This Row],[Facility]], 'LAB PRICES'!$C$1:$F$1, 0)) -> 5 | L137: =_xlfn.XLOOKUP( tblLabs[[#This Row],[Code]], 'LAB PRICES'!$A$2:$A$12, 'LAB PRICES'!$G$2:$G$12 ) -> 27
A138: 23S-074 | B138: R053 | C138: 7 | D138: 231209-2 | E138: FINALS | F138: L02 | G138: 45269 | I138: RM 235 | J138: ALLAB | K138: =INDEX('LAB PRICES'!$C$2:$F$12, MATCH(tblLabs[[#This Row],[Code]], 'LAB PRICES'!$A$2:$A$12, 0), MATCH(tblLabs[[#This Row],[Facility]], 'LAB PRICES'!$C$1:$F$1, 0)) -> 5 | L138: =_xlfn.XLOOKUP( tblLabs[[#This Row],[Code]], 'LAB PRICES'!$A$2:$A$12, 'LAB PRICES'!$G$2:$G$12 ) -> 27
A139: 23S-074 | B139: R053 | C139: 6 | D139: 231209-3 | E139: TEM | F139: L03 | G139: 45269 | I139: RM 235, 205 | J139: ALLAB | K139: =INDEX('LAB PRICES'!$C$2:$F$12, MATCH(tblLabs[[#This Row],[Code]], 'LAB PRICES'!$A$2:$A$12, 0), MATCH(tblLabs[[#This Row],[Facility]], 'LAB PRICES'!$C$1:$F$1, 0)) -> 30 | L139: =_xlfn.XLOOKUP( tblLabs[[#This Row],[Code]], 'LAB PRICES'!$A$2:$A$12, 'LAB PRICES'!$G$2:$G$12 ) -> 100
A140: 23S-074 | B140: R053 | C140: 18 | D140: 231209-6 | E140: PCM | F140: L01 | G140: 45268 | I140: RM 223 | J140: ALLAB | K140: =INDEX('LAB PRICES'!$C$2:$F$12, MATCH(tblLabs[[#This Row],[Code]], 'LAB PRICES'!$A$2:$A$12, 0), MATCH(tblLabs[[#This Row],[Facility]], 'LAB PRICES'!$C$1:$F$1, 0)) -> 5 | L140: =_xlfn.XLOOKUP( tblLabs[[#This Row],[Code]], 'LAB PRICES'!$A$2:$A$12, 'LAB PRICES'!$G$2:$G$12 ) -> 23
A141: 23S-074 | B141: R053 | C141: 12 | D141: 231209-7 | E141: PCM | F141: L01 | G141: 45268 | H141: Igor Groysman | I141: RM 205 | J141: ALLAB | K141: =INDEX('LAB PRICES'!$C$2:$F$12, MATCH(tblLabs[[#This Row],[Code]], 'LAB PRICES'!$A$2:$A$12, 0), MATCH(tblLabs[[#This Row],[Facility]], 'LAB PRICES'!$C$1:$F$1, 0)) -> 5 | L141: =_xlfn.XLOOKUP( tblLabs[[#This Row],[Code]], 'LAB PRICES'!$A$2:$A$12, 'LAB PRICES'!$G$2:$G$12 ) -> 23
A142: 23S-074 | B142: R053 | C142: 18 | D142: 231209-8 | E142: PCM | F142: L01 | G142: 45268 | H142: Igor Groysman | I142: RM 205 | J142: ALLAB | K142: =INDEX('LAB PRICES'!$C$2:$F$12, MATCH(tblLabs[[#This Row],[Code]], 'LAB PRICES'!$A$2:$A$12, 0), MATCH(tblLabs[[#This Row],[Facility]], 'LAB PRICES'!$C$1:$F$1, 0)) -> 5 | L142: =_xlfn.XLOOKUP( tblLabs[[#This Row],[Code]], 'LAB PRICES'!$A$2:$A$12, 'LAB PRICES'!$G$2:$G$12 ) -> 23
A143: 23S-074 | B143: R053 | C143: 6 | D143: 231209-9 | E143: TEM | F143: L03 | G143: 45269 | H143: Igor Groysman | I143: RM 205 | J143: ALLAB | K143: =INDEX('LAB PRICES'!$C$2:$F$12, MATCH(tblLabs[[#This Row],[Code]], 'LAB PRICES'!$A$2:$A$12, 0), MATCH(tblLabs[[#This Row],[Facility]], 'LAB PRICES'!$C$1:$F$1, 0)) -> 30 | L143: =_xlfn.XLOOKUP( tblLabs[[#This Row],[Code]], 'LAB PRICES'!$A$2:$A$12, 'LAB PRICES'!$G$2:$G$12 ) -> 100
A144: 23S-074 | B144: R053 | C144: 6 | D144: 240106-2 | E144: TEM | F144: L03 | G144: 45297 | H144: Igor Groysman | I144: RM 219, 225 | J144: ALLAB | K144: =INDEX('LAB PRICES'!$C$2:$F$12, MATCH(tblLabs[[#This Row],[Code]], 'LAB PRICES'!$A$2:$A$12, 0), MATCH(tblLabs[[#This Row],[Facility]], 'LAB PRICES'!$C$1:$F$1, 0)) -> 30 | L144: =_xlfn.XLOOKUP( tblLabs[[#This Row],[Code]], 'LAB PRICES'!$A$2:$A$12, 'LAB PRICES'!$G$2:$G$12 ) -> 100
A145: 23S-074 | B145: R053 | C145: 12 | D145: 240106-3 | E145: FINALS | F145: L02 | G145: 45297 | H145: Igor Groysman | I145: RM 219, 225 | J145: ALLAB | K145: =INDEX('LAB PRICES'!$C$2:$F$12, MATCH(tblLabs[[#This Row],[Code]], 'LAB PRICES'!$A$2:$A$12, 0), MATCH(tblLabs[[#This Row],[Facility]], 'LAB PRICES'!$C$1:$F$1, 0)) -> 5 | L145: =_xlfn.XLOOKUP( tblLabs[[#This Row],[Code]], 'LAB PRICES'!$A$2:$A$12, 'LAB PRICES'!$G$2:$G$12 ) -> 27
A146: 23S-074 | B146: R053 | C146: 12 | D146: 240106-7 | E146: PCM | F146: L01 | G146: 45296 | H146: Igor Groysman | I146: RM 219, 225 | J146: ALLAB | K146: =INDEX('LAB PRICES'!$C$2:$F$12, MATCH(tblLabs[[#This Row],[Code]], 'LAB PRICES'!$A$2:$A$12, 0), MATCH(tblLabs[[#This Row],[Facility]], 'LAB PRICES'!$C$1:$F$1, 0)) -> 5 | L146: =_xlfn.XLOOKUP( tblLabs[[#This Row],[Code]], 'LAB PRICES'!$A$2:$A$12, 'LAB PRICES'!$G$2:$G$12 ) -> 23
A147: 23S-074 | B147: R053 | C147: 18 | D147: 240106-8 | E147: PCM | F147: L01 | G147: 44931 | H147: Igor Groysman | I147: RM 219, 225 | J147: ALLAB | K147: =INDEX('LAB PRICES'!$C$2:$F$12, MATCH(tblLabs[[#This Row],[Code]], 'LAB PRICES'!$A$2:$A$12, 0), MATCH(tblLabs[[#This Row],[Facility]], 'LAB PRICES'!$C$1:$F$1, 0)) -> 5 | L147: =_xlfn.XLOOKUP( tblLabs[[#This Row],[Code]], 'LAB PRICES'!$A$2:$A$12, 'LAB PRICES'!$G$2:$G$12 ) -> 23
A148: 23S-075 | B148: K335 | C148: 5 | D148: 23-11-082 | E148: TEM | F148: L03 | G148: 45255 | H148: Chi Fei Hung | I148: RM 332, 332, 334 | J148: LTS | K148: =INDEX('LAB PRICES'!$C$2:$F$12, MATCH(tblLabs[[#This Row],[Code]], 'LAB PRICES'!$A$2:$A$12, 0), MATCH(tblLabs[[#This Row],[Facility]], 'LAB PRICES'!$C$1:$F$1, 0)) -> 40 | L148: =_xlfn.XLOOKUP( tblLabs[[#This Row],[Code]], 'LAB PRICES'!$A$2:$A$12, 'LAB PRICES'!$G$2:$G$12 ) -> 100
A149: 23S-075 | B149: K335 | C149: 12 | D149: 23-11-591 | E149: PCM | F149: L01 | G149: 45251 | H149: Chi Fei Hung | I149: RM 301, 305, 306, 307, 308, 320, 311 | J149: LTS | K149: =INDEX('LAB PRICES'!$C$2:$F$12, MATCH(tblLabs[[#This Row],[Code]], 'LAB PRICES'!$A$2:$A$12, 0), MATCH(tblLabs[[#This Row],[Facility]], 'LAB PRICES'!$C$1:$F$1, 0)) -> 6 | L149: =_xlfn.XLOOKUP( tblLabs[[#This Row],[Code]], 'LAB PRICES'!$A$2:$A$12, 'LAB PRICES'!$G$2:$G$12 ) -> 23
A150: 23S-075 | B150: K335 | C150: 12 | D150: 23-11-631 | E150: PCM | F150: L01 | G150: 45252 | H150: Chi Fei Hung | I150: RM 333, 334 | J150: LTS | K150: =INDEX('LAB PRICES'!$C$2:$F$12, MATCH(tblLabs[[#This Row],[Code]], 'LAB PRICES'!$A$2:$A$12, 0), MATCH(tblLabs[[#This Row],[Facility]], 'LAB PRICES'!$C$1:$F$1, 0)) -> 6 | L150: =_xlfn.XLOOKUP( tblLabs[[#This Row],[Code]], 'LAB PRICES'!$A$2:$A$12, 'LAB PRICES'!$G$2:$G$12 ) -> 23
A151: 23S-075 | B151: K335 | C151: 14 | D151: 23-11-641 | E151: PCM | F151: L01 | G151: 45254 | H151: Chi Fei Hung | I151: RM 332, 333, 334 | J151: LTS | K151: =INDEX('LAB PRICES'!$C$2:$F$12, MATCH(tblLabs[[#This Row],[Code]], 'LAB PRICES'!$A$2:$A$12, 0), MATCH(tblLabs[[#This Row],[Facility]], 'LAB PRICES'!$C$1:$F$1, 0)) -> 6 | L151: =_xlfn.XLOOKUP( tblLabs[[#This Row],[Code]], 'LAB PRICES'!$A$2:$A$12, 'LAB PRICES'!$G$2:$G$12 ) -> 23
A152: 23S-075 | B152: K335 | C152: 14 | D152: 23-11-677 | E152: PCM | F152: L01 | G152: 45255 | H152: Chi Fei Hung | I152: RM 332, 333, 334 | J152: LTS | K152: =INDEX('LAB PRICES'!$C$2:$F$12, MATCH(tblLabs[[#This Row],[Code]], 'LAB PRICES'!$A$2:$A$12, 0), MATCH(tblLabs[[#This Row],[Facility]], 'LAB PRICES'!$C$1:$F$1, 0)) -> 6 | L152: =_xlfn.XLOOKUP( tblLabs[[#This Row],[Code]], 'LAB PRICES'!$A$2:$A$12, 'LAB PRICES'!$G$2:$G$12 ) -> 23
... A582: 24S-111 | B582: K209 | C582: 8 | D582: 250405-7 | E582: PCM | F582: L01 | G582: 45751 | H582: Igor Groysman | I582: CAFÉ | J582: ALLAB | K582: =INDEX('LAB PRICES'!$C$2:$F$12, MATCH(tblLabs[[#This Row],[Code]], 'LAB PRICES'!$A$2:$A$12, 0), MATCH(tblLabs[[#This Row],[Facility]], 'LAB PRICES'!$C$1:$F$1, 0)) -> 5 | L582: =_xlfn.XLOOKUP( tblLabs[[#This Row],[Code]], 'LAB PRICES'!$A$2:$A$12, 'LAB PRICES'!$G$2:$G$12 ) -> 23
A583: 24S-111 | B583: K209 | C583: 3 | D583: 250405-8 | E583: TEM | F583: L03 | G583: 45752 | H583: Igor Groysman | J583: ALLAB | K583: =INDEX('LAB PRICES'!$C$2:$F$12, MATCH(tblLabs[[#This Row],[Code]], 'LAB PRICES'!$A$2:$A$12, 0), MATCH(tblLabs[[#This Row],[Facility]], 'LAB PRICES'!$C$1:$F$1, 0)) -> 30 | L583: =_xlfn.XLOOKUP( tblLabs[[#This Row],[Code]], 'LAB PRICES'!$A$2:$A$12, 'LAB PRICES'!$G$2:$G$12 ) -> 100
A584: 24S-111 | B584: K209 | C584: 12 | D584: 25-04-069-PL | E584: PLM | F584: L04 | G584: 45754 | H584: Cornel Albu | I584: 2ND FL CORRIDOR BY RM 265 | J584: LTS | K584: =INDEX('LAB PRICES'!$C$2:$F$12, MATCH(tblLabs[[#This Row],[Code]], 'LAB PRICES'!$A$2:$A$12, 0), MATCH(tblLabs[[#This Row],[Facility]], 'LAB PRICES'!$C$1:$F$1, 0)) -> 16 | L584: =_xlfn.XLOOKUP( tblLabs[[#This Row],[Code]], 'LAB PRICES'!$A$2:$A$12, 'LAB PRICES'!$G$2:$G$12 ) -> 23
A585: 24S-111 | B585: K209 | C585: 3 | D585: 25-04-069-PN | E585: PLM-NOB | F585: L05 | G585: 45754 | H585: Cornel Albu | I585: 2ND FL CORRIDOR BY RM 265 | J585: LTS | K585: =INDEX('LAB PRICES'!$C$2:$F$12, MATCH(tblLabs[[#This Row],[Code]], 'LAB PRICES'!$A$2:$A$12, 0), MATCH(tblLabs[[#This Row],[Facility]], 'LAB PRICES'!$C$1:$F$1, 0)) -> 6 | L585: =_xlfn.XLOOKUP( tblLabs[[#This Row],[Code]], 'LAB PRICES'!$A$2:$A$12, 'LAB PRICES'!$G$2:$G$12 ) -> 40
A586: 24S-111 | B586: K209 | C586: 3 | D586: 25-04-069-TN | E586: TEM-NOB | F586: L06 | G586: 45754 | H586: Cornel Albu | I586: 2ND FL CORRIDOR BY RM 265 | J586: LTS | K586: =INDEX('LAB PRICES'!$C$2:$F$12, MATCH(tblLabs[[#This Row],[Code]], 'LAB PRICES'!$A$2:$A$12, 0), MATCH(tblLabs[[#This Row],[Facility]], 'LAB PRICES'!$C$1:$F$1, 0)) -> 26 | L586: =_xlfn.XLOOKUP( tblLabs[[#This Row],[Code]], 'LAB PRICES'!$A$2:$A$12, 'LAB PRICES'!$G$2:$G$12 ) -> 70

Sheet PAYROLL
A1: EMPLOYEE_NAME | B1: CODE | C1: HOURLY_RATE | D1: WEEK_PAID | E1: DATE_WORKED | F1: WEEK ENDING DATE | G1: HOURS_WORKED | H1: JOB_TYPE | I1: JOBID | J1: BID | K1: EXPENSES | L1: NOTE
A2: Chi Fei Hung | B2: 1 | C2: 38 | D2: 44926 | E2: 44913 | G2: 15.5 | I2: 23S-038 | J2: Q059
A3: Chi Fei Hung | B3: 1 | C3: 38 | D3: 44926 | E3: 44917 | G3: 5 | I3: 23S-038 | J3: Q059
A4: Chi Fei Hung | B4: 1 | C4: 38 | D4: 44926 | E4: 44918 | G4: 10 | I4: 22S-081 | J4: X843
A5: Chi Fei Hung | B5: 1 | C5: 38 | D5: 44926 | E5: 44919 | G5: 16.5 | I5: 22S-081 | J5: X843
A6: Cornel Albu | B6: 1 | C6: 38 | D6: 44926 | E6: 44913 | G6: 10.5 | I6: 22S-072 | J6: K127
A7: Cornel Albu | B7: 1 | C7: 38 | D7: 44926 | E7: 44916 | G7: 4.5 | I7: 22S-025 | J7: Q112
A8: Cornel Albu | B8: 1 | C8: 38 | D8: 44926 | E8: 44917 | G8: 5.5 | I8: 22S-018 | J8: M137
A9: Cornel Albu | B9: 1 | C9: 38 | D9: 44926 | E9: 44918 | G9: 7.5 | I9: 22S-018 | J9: M137
A10: Cornel Albu | B10: 1 | C10: 38 | D10: 44926 | E10: 44919 | G10: 12.5 | I10: 22S-018 | J10: M137
A11: Joi Fei Hung | B11: 1 | C11: 38 | D11: 44926 | E11: 44917 | G11: 5 | I11: 22S-050 | J11: M164
A12: Joi Fei Hung | B12: 1 | C12: 38 | D12: 44926 | E12: 44918 | G12: 6.5 | I12: 22S-050 | J12: Q112
A13: Joi Fei Hung | B13: 1 | C13: 38 | D13: 44926 | E13: 44919 | G13: 21 | I13: 22S-050 | J13: Q112
A14: Patricia Dros | B14: 0 | C14: 28 | D14: 44926 | E14: 44910 | G14: 8 | I14: NA
A15: Patricia Dros | B15: 0 | C15: 28 | D15: 44926 | E15: 44911 | G15: 8 | I15: NA
A16: Patricia Dros | B16: 0 | C16: 28 | D16: 44926 | E16: 44913 | G16: 0 | I16: NA
A17: Patricia Dros | B17: 0 | C17: 28 | D17: 44926 | E17: 44914 | G17: 7 | I17: NA
A18: Patricia Dros | B18: 0 | C18: 28 | D18: 44926 | E18: 44915 | G18: 7 | I18: NA
A19: Patricia Dros | B19: 0 | C19: 28 | D19: 44926 | E19: 44916 | G19: 7 | I19: NA
A20: Patricia Dros | B20: 0 | C20: 28 | D20: 44926 | E20: 44917 | G20: 7 | I20: NA
A21: Patricia Dros | B21: 0 | C21: 28 | D21: 44926 | E21: 44918 | G21: 7 | I21: NA
A22: Patricia Dros | B22: 0 | C22: 28 | D22: 44926 | E22: 44919 | G22: 0 | I22: NA
A23: Shalva Saghashvili | B23: 1 | C23: 38 | D23: 44926 | E23: 44918 | G23: 6.5 | I23: 22S-021 | J23: X843
A24: Shalva Saghashvili | B24: 1 | C24: 38 | D24: 44926 | E24: 44919 | G24: 17 | I24: 22S-021 | J24: X843
A25: Tatiana Ciobanu | B25: 1 | C25: 33 | D25: 44926 | E25: 44875 | G25: 5.5 | I25: 21S-102 | J25: K061
A26: Tatiana Ciobanu | B26: 1 | C26: 33 | D26: 44926 | E26: 44876 | G26: 6.5 | I26: 21S-102 | J26: K061
A27: Chi Fei Hung | B27: 1 | C27: 38 | D27: 44933 | E27: 44921 | G27: 7 | I27: 22S-038 | J27: Q059
A28: Chi Fei Hung | B28: 1 | C28: 38 | D28: 44933 | E28: 44922 | G28: 24 | I28: 22S-038 | J28: Q059
A29: Chi Fei Hung | B29: 1 | C29: 38 | D29: 44933 | E29: 44923 | G29: 19 | I29: 22S-038 | J29: Q059
A30: Chi Fei Hung | B30: 1 | C30: 38 | D30: 44933 | E30: 44924 | G30: 15.5 | I30: 22S-038 | J30: Q059
A31: Chi Fei Hung | B31: 1 | C31: 38 | D31: 44933 | E31: 44925 | G31: 9 | I31: 22S-038 | J31: Q059
A32: Chi Fei Hung | B32: 1 | C32: 38 | D32: 44933 | E32: 44925 | G32: 9.5 | I32: 22S-085 | J32: K127
A33: Chi Fei Hung | B33: 1 | C33: 38 | D33: 44933 | E33: 44926 | G33: 17 | I33: 22S-085 | J33: K127
A34: Cornel Albu | B34: 1 | C34: 38 | D34: 44933 | E34: 44922 | G34: 16.5 | I34: 22S-018 | J34: M137
... A44: Joi Fei Hung | B44: 1 | C44: 38 | D44: 44933 | E44: 44925 | G44: 9 | I44: 22S-050 | J44: M164
A45: Patricia Dros | B45: 0 | C45: 28 | D45: 44933 | E45: 44920 | G45: 0 | I45: NA
A46: Patricia Dros | B46: 0 | C46: 28 | D46: 44933 | E46: 44921 | G46: 7 | I46: NA
A47: Patricia Dros | B47: 0 | C47: 28 | D47: 44933 | E47: 44922 | G47: 7 | I47: NA
A48: Patricia Dros | B48: 0 | C48: 28 | D48: 44933 | E48: 44923 | G48: 7 | I48: NA
A49: Patricia Dros | B49: 0 | C49: 28 | D49: 44933 | E49: 44924 | G49: 7 | I49: NA
A50: Patricia Dros | B50: 0 | C50: 28 | D50: 44933 | E50: 44925 | G50: 7 | I50: NA
A51: Patricia Dros | B51: 0 | C51: 28 | D51: 44933 | E51: 44926 | G51: 0 | I51: NA
A52: Chi Fei Hung | B52: 1 | C52: 38 | D52: 44940 | E52: 44931 | G52: 4.5 | I52: 22S-044 | J52: Q801
A53: Chi Fei Hung | B53: 1 | C53: 38 | D53: 44940 | E53: 44932 | G53: 6.5 | I53: 22S-044 | J53: Q801
A54: Chi Fei Hung | B54: 1 | C54: 38 | D54: 44940 | E54: 44933 | G54: 19.5 | I54: 22S-044 | J54: Q801
A55: Patricia Dros | B55: 0 | C55: 28 | D55: 44940 | E55: 44928 | G55: 8 | I55: NA
A56: Patricia Dros | B56: 0 | C56: 28 | D56: 44940 | E56: 44929 | G56: 7 | I56: NA
A57: Patricia Dros | B57: 0 | C57: 28 | D57: 44940 | E57: 44930 | G57: 7 | I57: NA
A58: Patricia Dros | B58: 0 | C58: 28 | D58: 44940 | E58: 44931 | G58: 7 | I58: NA
A59: Patricia Dros | B59: 0 | C59: 28 | D59: 44940 | E59: 44932 | G59: 7 | I59: NA | K59: 54.13
A60: Chi Fei Hung | B60: 1 | C60: 38 | D60: 44947 | E60: 44938 | G60: 5 | I60: 22S-043 | J60: M098
A61: Chi Fei Hung | B61: 1 | C61: 38 | D61: 44947 | E61: 44939 | G61: 7.5 | I61: 22S-043 | J61: M098 | K61: 13.1
A62: Chi Fei Hung | B62: 1 | C62: 38 | D62: 44947 | E62: 44940 | G62: 18.5 | I62: 22S-043 | J62: M098 | K62: 13.1
A63: Cornel Albu | B63: 1 | C63: 38 | D63: 44947 | E63: 44938 | G63: 4 | I63: 22S-068 | J63: M137
A64: Cornel Albu | B64: 1 | C64: 38 | D64: 44947 | E64: 44939 | G64: 6.5 | I64: 22S-068 | J64: M137
A65: Cornel Albu | B65: 1 | C65: 38 | D65: 44947 | E65: 44940 | G65: 12 | I65: 22S-068 | J65: M137
A66: Joi Fei Hung | B66: 1 | C66: 38 | D66: 44947 | E66: 44945 | G66: 5 | I66: 22S-068 | J66: M137
A67: Joi Fei Hung | B67: 1 | C67: 38 | D67: 44947 | E67: 44946 | G67: 6.5 | I67: 22S-068 | J67: M137
A68: Joi Fei Hung | B68: 1 | C68: 38 | D68: 44947 | E68: 44947 | G68: 20.5 | I68: 22S-068 | J68: M137
A69: Patricia Dros | B69: 0 | C69: 28 | D69: 44947 | E69: 44936 | G69: 7 | I69: NA
A70: Patricia Dros | B70: 0 | C70: 28 | D70: 44947 | E70: 44937 | G70: 7 | I70: NA
A71: Patricia Dros | B71: 0 | C71: 28 | D71: 44947 | E71: 44938 | G71: 7 | I71: NA
A72: Patricia Dros | B72: 0 | C72: 28 | D72: 44947 | E72: 44939 | G72: 7 | I72: NA | K72: 47.71
A73: Patricia Dros | B73: 0 | C73: 28 | D73: 44947 | E73: 44942 | G73: 7 | I73: NA
A74: Patricia Dros | B74: 0 | C74: 28 | D74: 44947 | E74: 44943 | G74: 7 | I74: NA
A75: Patricia Dros | B75: 0 | C75: 28 | D75: 44947 | E75: 44944 | G75: 7 | I75: NA
A76: Patricia Dros | B76: 0 | C76: 28 | D76: 44947 | E76: 44945 | G76: 7 | I76: NA
A77: Patricia Dros | B77: 0 | C77: 28 | D77: 44947 | E77: 44946 | G77: 7 | I77: NA
A78: Chi Fei Hung | B78: 1 | C78: 38 | D78: 44953 | E78: 44945 | G78: 5 | I78: 22S-043 | J78: M098
A79: Chi Fei Hung | B79: 1 | C79: 38 | D79: 44953 | E79: 44946 | G79: 7.5 | I79: 22S-043 | J79: M098 | K79: 13.9
A80: Chi Fei Hung | B80: 1 | C80: 38 | D80: 44953 | E80: 44947 | G80: 18.5 | I80: 22S-043 | J80: M098 | K80: 13.9
A81: Chi Fei Hung | B81: 1 | C81: 38 | D81: 44953 | E81: 44947 | G81: 4 | I81: 22S-045 | J81: M435 | K81: 13.9
A82: Chi Fei Hung | B82: 1 | C82: 38 | D82: 44968 | E82: 44959 | G82: 5 | I82: 22S-064 | J82: K600
A83: Chi Fei Hung | B83: 1 | C83: 38 | D83: 44968 | E83: 44960 | G83: 7.5 | I83: 22S-064 | J83: K600
A84: Chi Fei Hung | B84: 1 | C84: 38 | D84: 44968 | E84: 44961 | G84: 19 | I84: 22S-064 | J84: K600
A85: Igor Groysman | B85: 1 | C85: 38 | D85: 44968 | E85: 44784 | G85: 4.5 | I85: 22S-027 | J85: K055
A86: Igor Groysman | B86: 1 | C86: 38 | D86: 44968 | E86: 44785 | G86: 7.5 | I86: 22S-027 | J86: K055
A87: Igor Groysman | B87: 1 | C87: 38 | D87: 44968 | E87: 44786 | G87: 20 | I87: 22S-027 | J87: K055
A88: Igor Groysman | B88: 1 | C88: 38 | D88: 44968 | E88: 44787 | G88: 5 | I88: 22S-027 | J88: K055
A89: Patricia Dros | B89: 0 | C89: 28 | D89: 44968 | E89: 44957 | G89: 6.5 | I89: NA
A90: Patricia Dros | B90: 0 | C90: 28 | D90: 44968 | E90: 44959 | G90: 7 | I90: NA
A91: Patricia Dros | B91: 0 | C91: 28 | D91: 44968 | E91: 44960 | G91: 7.5 | I91: NA
A92: Tatiana Ciobanu | B92: 1 | C92: 38 | D92: 44968 | E92: 44939 | G92: 6.5 | I92: 22S-068 | J92: M137
A93: Tatiana Ciobanu | B93: 1 | C93: 38 | D93: 44968 | E93: 44940 | G93: 19.5 | I93: 22S-068 | J93: M137
A94: Chi Fei Hung | B94: 1 | C94: 38 | D94: 45143 | E94: 45130 | G94: 19.5 | I94: 22S-069 | J94: Q216
A95: Chi Fei Hung | B95: 1 | C95: 38 | D95: 45143 | E95: 45131 | G95: 4.5 | I95: 23S-042 | J95: K364
A96: Chi Fei Hung | B96: 1 | C96: 38 | D96: 45143 | E96: 45132 | G96: 16.5 | I96: 23S-042 | J96: K364
A97: Chi Fei Hung | B97: 1 | C97: 38 | D97: 45143 | E97: 45133 | G97: 15.5 | I97: 23S-042 | J97: K364
A98: Chi Fei Hung | B98: 1 | C98: 38 | D98: 45143 | E98: 45134 | G98: 4.5 | I98: 23S-025 | J98: X041
A99: Chi Fei Hung | B99: 1 | C99: 38 | D99: 45143 | E99: 45135 | G99: 4.5 | I99: 23S-025 | J99: X041
A100: Chi Fei Hung | B100: 1 | C100: 38 | D100: 45143 | E100: 45135 | G100: 6.5 | I100: 23S-019 | J100: M490
A101: Chi Fei Hung | B101: 1 | C101: 38 | D101: 45143 | E101: 45136 | G101: 19 | I101: 23S-019 | J101: M490
A102: Joi Fei Hung | B102: 1 | C102: 38 | D102: 45143 | E102: 45134 | G102: 6 | I102: 23S-045 | J102: M115
A103: Joi Fei Hung | B103: 1 | C103: 38 | D103: 45143 | E103: 45135 | G103: 6.5 | I103: 23S-045 | J103: M115
A104: Joi Fei Hung | B104: 1 | C104: 38 | D104: 45143 | E104: 45136 | G104: 24 | I104: 23S-045 | J104: M115
A105: Patricia Dros | B105: 0 | C105: 28 | D105: 45143 | E105: 45130 | G105: 0 | I105: NA
A106: Patricia Dros | B106: 0 | C106: 28 | D106: 45143 | E106: 45131 | G106: 7 | I106: NA
A107: Patricia Dros | B107: 0 | C107: 28 | D107: 45143 | E107: 45132 | G107: 7 | I107: NA
A108: Patricia Dros | B108: 0 | C108: 28 | D108: 45143 | E108: 45133 | G108: 7 | I108: NA
A109: Patricia Dros | B109: 0 | C109: 28 | D109: 45143 | E109: 45134 | G109: 7 | I109: NA
...

Sheet LAB PRICES
A1: Code | B1: SAMPLE_TYPE | C1: LTS | D1: ALLAB | E1: ATC | F1: KAM | G1: SCA_FEE_SCHED
A2: L01 | B2: PCM | C2: 6 | D2: 5 | E2: 6 | F2: 0 | G2: 23
A3: L02 | B3: PCM-FINALS | C3: 6 | D3: 5 | E3: 6 | F3: 0 | G3: 27
A4: L03 | B4: TEM | C4: 40 | D4: 30 | E4: 40 | F4: 0 | G4: 100
A5: L04 | B5: PLM | C5: 16 | D5: 5 | E5: 0 | F5: 0 | G5: 23
A6: L05 | B6: PLM-NOB | C6: 6 | D6: 9.5 | E6: 0 | F6: 10 | G6: 40
A7: L06 | B7: TEM-NOB | C7: 26 | D7: 20 | E7: 0 | F7: 25 | G7: 70
A8: L07 | B8: PLM-FRI | C8: 6 | D8: 6 | E8: 8 | F8: 8 | G8: 23
A9: L08 | B9: LEAD WIPE | C9: 14 | D9: 12 | E9: 14 | F9: 14 | G9: 28
A10: L09 | B10: LEAD PAINT CHIPS | C10: 14 | D10: 14 | E10: 0 | F10: 0 | G10: 25
A11: L10 | B11: PCB | C11: 20 | D11: 25 | E11: 0 | F11: 80 | G11: 140
A12: L11 | B12: SLIDE | C12: 4 | D12: 5 | E12: 0 | F12: 0 | G12: 22

Sheet PROJECT LOG
A1: Jobs for Project | O1: CONTRACT # | P1: C000015869
A2: 2023 | B2: X107 | C2: 23S-052 | D2: M115 | E2: 23S-045 | F2: K335 | G2: 23S-075 | H2: R053 | I2: 23S-074 | J2: Q165 | K2: 23S-103 | O2: Contract Value | P2: 6000000
B3: X075 | C3: 23S-114 | D3: M169 | E3: 23S-078 | F3: K055 | G3: 23S-110 | H3: R460 | I3: 23S-024 | J3: Q205 | K3: 23S-006 | O3: Contract Execution Date | P3: 44621
O4: Contract Expiration Date | P4: 45716
A5: 2024 | B5: X049 | C5: 24S-039 | D5: M064 | E5: 24S-042 | F5: K261 | G5: 24S-007 | H5: R002 | I5: 24S-084 | J5: Q442 | K5: 24S-032 | O5: Solicitation # | P5: 22-00003R
B6: X470 | C6: 24S-070 | D6: M192 | E6: 24S-006 | F6: K209 | G6: 24S-111 | H6: R455 | I6: 24S-050 | J6: Q188 | K6: 24S-101
A8: 2025 | B8: X107 | C8: 25S-010 | D8: M169 | E8: 25S-078
A11: I NEED TO
B12: Learn to create a data model
B13: Create a data model
A19: 45791 | B19: LTS INCREASED PRICE OF TEM-AIR FROM $40 TO $50

Sheet ALLAB INOVICES
A1: Date | B1: Num | C1: Memo | D1: Column1 | E1: Amount
A2: 44227 | B2: 210113-30 | C2: 710 Riverside Drive NY | E2: -142.5
A3: 44227 | B3: 210126-19 | C3: 26-42 169th Street, Flushing NY | E3: -304.5
A4: 44255 | B4: 210218-1 | C4: 4790 Broadway NY | E4: -57
A5: 44316 | B5: 210414-51 | C5: 133 East 80th Street | E5: -178.5
A6: 44377 | B6: 210520-11 | C6: 127 Manhattan Avenue New York, NY | E6: -898.5
A7: 44377 | B7: 210626-14 | C7: 5 Quincy Street Brooklyn, NY | E7: -283.5
A8: 44377 | B8: 210630-29 | C8: 191 Joralemon Street Brookly, NY | E8: -619.5
A9: 44408 | B9: 210702-24 | C9: 191 Joralemon Street, Brooklyn | E9: -177
A10: 44408 | B10: 210702-25 | C10: 27-24 Jackson Avenue Queens | E10: -108
A11: 44408 | B11: 210702-26 | C11: 72 Spring Street | E11: -213
A12: 44408 | B12: 210702-27 | C12: 27-24 Jackson Avenue Queens | E12: -178.5
A13: 44408 | B13: 210702-28 | C13: 25-36 21st Street Queens, NY | E13: -1048.5
... A525: 45565 | B525: 240910-67 | C525: Project #23S-132 | E525: -60
A526: 45565 | B526: 240911-40 | E526: -222
A527: 45565 | B527: 240911-41 | E527: -60
A528: 45565 | B528: 240911-42 | E528: -265.5
A529: 45565 | B529: 240911-46 | C529: PROJ# 23S-132 | E529: -60
A530: 45565 | B530: 240912-55 | C530: PROJ# 23S-132 | E530: -60
A531: 45565 | B531: 240913-56 | C531: PROJ# 23S-132 | E531: -60
A532: 45565 | B532: 240914-30 | C532: PROJ# 24S-094 | E532: -70
A533: 45565 | B533: 240915-2 | C533: PROJ# 24S-098 | E533: -40
A534: 45565 | B534: 240915-3 | C534: PROJ# 24S-098 | E534: -30
A535: 45565 | B535: 240915-13 | E535: -135
A536: 45565 | B536: 240921-16 | E536: -70
A537: 45565 | B537: 240921-17 | E537: -30
A538: 45565 | B538: 240921-23 | C538: PROJ# 23S-078 | E538: -35
A539: 45565 | B539: 240922-3 | C539: PROJ# 24S-099 | E539: -60
A540: 45565 | B540: 240922-4 | C540: PROJ# 24S-099 | E540: -90
A541: 45565 | B541: 240922-5 | C541: PROJ# 24S-099 | E541: -50
A542: 45565 | B542: 240922-7 | C542: PROJ# 24S-099 | E542: -60
A543: 45565 | B543: 240922-8 | C543: PROJ# 24S-099 | E543: -40
A544: 45565 | B544: 240925-48 | C544: PROJ# 23S-132 | E544: -45
A545: 45565 | B545: 240926-61 | C545: PROJ# 23S-132 | E545: -45
A546: 45565 | B546: 240928-1 | C546: PROJ# 24S-020 | E546: -60
A547: 45565 | B547: 240928-2 | C547: PROJ# 24S-020 | E547: -60
A548: 45565 | B548: 240929-1 | C548: PROJ# 24S-020 | E548: -60
A549: 45565 | B549: 240929-2 | C549: PROJ# 24S-020 | E549: -50
... A557: 45596 | B557: 241005-5 | C557: PROJ# 24S-112 | E557: -25
A558: 45596 | B558: 241006-1 | E558: -88.5
A559: 45596 | B559: 241006-2 | E559: -80
A560: 45596 | B560: 241006-3 | E560: -651
A561: 45596 | B561: 241006-4 | C561: 139063 | E561: -1152.5
A562: 45596 | B562: 241009-1 | C562: PROJ# 23S-132 | E562: -60
A563: 45596 | B563: 241009-50 | C563: PROJ# 23S-132 | E563: -60
A564: 45596 | B564: 241010-57 | C564: PROJ# 23S-132 | E564: -60
A565: 45596 | B565: 241013-2 | C565: PROJ# 24S-063 | E565: -60
A566: 45596 | B566: 241013-3 | C566: PROJ# 24S-063 | E566: -35
A567: 45596 | B567: 241014-13 | C567: PROJ# 24S-110 | E567: -85
A568: 45596 | B568: 241027-1 | C568: PROJ# 24S-118 | E568: -70
A569: 45596 | B569: 241027-2 | C569: PROJ# 24S-118 | E569: -25
A570: 45596 | B570: 241030-1 | C570: PROJ# 24S-121 | E570: -65
A571: 45596 | B571: 241030-2 | C571: PROJ# 24S-121 | E571: -40
A572: 45598 | B572: JAN - JUN 2024 | C572: JAN - JUN 2024 | E572: -18981
... A679: 45688 | B679: 250116-52 | C679: X005 | E679: -110
A680: 45688 | B680: 250122-59 | E680: -228.5
A681: 45688 | B681: 250131-50 | C681: Q420 | E681: -1543.5
A682: 45688 | B682: 250131-51 | C682: Q420 | E682: -50
A683: 45688 | B683: 250125-25 | C683: 23S-132 | E683: -60
A684: 45688 | B684: 250131-37 | C684: 24S-102 | E684: -60
A685: 45688 | B685: 250126-10 | C685: 23S-132 | E685: -207
A686: 45688 | B686: 250130-56 | C686: 25S-006 | E686: -1053
A687: 45716 | B687: 250208-25 | C687: 20-21 35TH STREET | E687: -625.5
A688: 45716 | B688: 250202-1 | C688: 24S-102 | E688: -40
A689: 45716 | B689: 250202-2 | C689: 24S-102 | E689: -90
A690: 45716 | B690: 250202-3 | C690: 24S-102 | E690: -60
A691: 45716 | B691: 250202-4 | C691: 24S-102 | E691: -60
A692: 45716 | B692: 250202-5 | C692: 24S-102 | E692: -60
... A785: 45838 | B785: 250626-13 | C785: 110 Central Park South,NY,NY Apt # 5B | E785: -430.5

Sheet LTS INVOICES
A1: INV# | B1: BID | C1: JOB NO | D1: Item | E1: JOB NUMBER | F1: QTY | G1: RATE | H1: TOTAL
A2: 75992 | B2: M115 | C2: 24S-117 | D2: PCM(24HRS) | E2: 25-06-148 | F2: 12 | G2: 6 | H2: 72
A3: 75992 | B3: M115 | C3: 24S-117 | D3: PCM(24HRS) | E3: 25-06-149 | F3: 12 | G3: 6 | H3: 72
A4: 75992 | B4: M115 | C4: 24S-117 | D4: PCM(24HRS) | E4: 25-06-185 | F4: 12 | G4: 6 | H4: 72
A5: 75992 | B5: M115 | C5: 24S-117 | D5: PCM(24HRS) | E5: 25-06-186 | F5: 14 | G5: 6 | H5: 84
A6: 75992 | B6: M115 | C6: 24S-117 | D6: PCM(24HRS) | E6: 25-06-258 | F6: 6 | G6: 6 | H6: 36
A7: 75992 | B7: M115 | C7: 24S-117 | D7: PCM(24HRS) | E7: 25-06-259 | F7: 8 | G7: 6 | H7: 48
A8: 75992 | B8: M115 | C8: 24S-117 | D8: PCM(6HRS) | E8: 25-06-260 | F8: 12 | G8: 6 | H8: 72
A9: 75992 | B9: M115 | C9: 24S-117 | D9: PCM(24HRS) | E9: 25-06-261 | F9: 14 | G9: 6 | H9: 84
A10: 75992 | B10: M115 | C10: 24S-117 | D10: PCM(1HR) | E10: 25-06-262 | F10: 12 | G10: 6 | H10: 72
A11: 75887 | B11: K324 | D11: PLM | E11: 24-01-124 | F11: 6 | G11: 16 | H11: 96
A12: 75887 | B12: K324 | D12: TEM-NOB | E12: 24-01-124 | F12: 6 | G12: 26 | H12: 156
A13: 75887 | B13: K324 | D13: PLM-NOB | E13: 24-01-124 | F13: 30 | G13: 6 | H13: 180
A14: 75570 | B14: Q165 | C14: 23S-103 | D14: TEM-AIR | E14: 25-05-048 | F14: 5 | G14: 40 | H14: 200
A15: 75989 | B15: Q217 | C15: 23S-071 | D15: PCM(1HR) | E15: 25-03-092 | F15: 15 | G15: 6 | H15: =F15*G15 -> 90
A16: 75989 | B16: Q217 | C16: 23S-071 | D16: PCM(1HR) | E16: 25-03-119 | F16: 7 | G16: 6 | H16: =F16*G16 -> 42
A17: 75989 | B17: Q217 | C17: 23S-071 | D17: PCM(1HR) | E17: 25-03-325 | F17: 7 | G17: 6 | H17: =F17*G17 -> 42
A18: 75989 | B18: Q217 | C18: 23S-071 | D18: PCM(1HR) | E18: 25-03-326 | F18: 8 | G18: 6 | H18: =F18*G18 -> 48
A19: 76234 | B19: Q400 | D19: PLM-NOB | E19: 25-05-244 | F19: 3 | G19: 16 | H19: =F19*G19 -> 48
A20: 76234 | B20: Q400 | D20: TEM-NOB | E20: 25-05-244 | F20: 3 | G20: 26 | H20: =F20*G20 -> 78
A21: 76234 | B21: Q400 | D21: PLM | E21: 25-05-244 | F21: 6 | G21: 6 | H21: =F21*G21 -> 36
A22: 76347 | B22: K480 | C22: 19S-001 | D22: TEM | E22: 19-07-169 | F22: 6 | G22: 40 | H22: =F22*G22 -> 240
A23: 76681 | B23: M140 | C23: 23S-055 | D23: TEM | E23: 25-07-136 | F23: 5 | G23: 40 | H23: =F23*G23 -> 200
A24: 75571 | B24: X101 | C24: 24S-143 | D24: TEM | E24: 25-05-042 | F24: 5 | G24: 40 | H24: =F24*G24 -> 200
A25: 75481 | B25: M169 | C25: 23S-078 | D25: PCM (1HR) | E25: 25-04-944 | F25: 12 | G25: 6 | H25: =F25*G25 -> 72
A26: 75481 | B26: M169 | C26: 23S-078 | D26: PCM(24HRS) | E26: 25-04-945 | F26: 6 | G26: 6 | H26: =F26*G26 -> 36
A27: 75481 | B27: M169 | C27: 23S-078 | D27: PCM(24HRS) | E27: 25-04-946 | F27: 14 | G27: 6 | H27: =F27*G27 -> 84
A28: 75481 | B28: M169 | C28: 23S-078 | D28: PCM(24HRS) | E28: 25-04-947 | F28: 8 | G28: 6 | H28: =F28*G28 -> 48
A29: 75481 | B29: M169 | C29: 23S-078 | D29: PCM(24HRS) | E29: 25-04-998 | F29: 12 | G29: 6 | H29: =F29*G29 -> 72
A30: 75481 | B30: M169 | C30: 23S-078 | D30: PCM(24HRS) | E30: 25-04-999 | F30: 14 | G30: 6 | H30: =F30*G30 -> 84
A31: 75481 | B31: M169 | C31: 23S-078 | D31: PCM(24HRS) | E31: 25-04-1000 | F31: 12 | G31: 6 | H31: =F31*G31 -> 72
A32: 65708 | B32: X107 | C32: 23S-052 | D32: TEM-AIR | E32: 23-10-071 | F32: 5 | G32: 40 | H32: =F32*G32 -> 200
A33: 65708 | B33: X107 | C33: 23S-052 | D33: TEM-AIR | E33: 23-10-072 | F33: 5 | G33: 40 | H33: =F33*G33 -> 200
... A103: 63982 | B103: M115 | C103: 23S-045 | D103: TEM-AIR | E103: 23-08-059 | F103: 6 | G103: 40 | H103: =F103*G103 -> 240
A104: 63882 | B104: M115 | C104: 23S-045 | D104: TEM-AIR | F104: 9 | G104: 40 | H104: =F104*G104 -> 360
A105: 65764 | B105: M169 | C105: 23S-078 | D105: PLM | E105: 23-09-031 | F105: 12 | G105: 6 | H105: =F105*G105 -> 72
A106: 65764 | B106: M169 | C106: 23S-078 | D106: PLM-NOB | E106: 23-09-031 | F106: 48 | G106: 16 | H106: =F106*G106 -> 768
A107: 65764 | B107: M169 | C107: 23S-078 | D107: TEM-NOB | E107: 23-09-031 | F107: 47 | G107: 26 | H107: =F107*G107 -> 1222
A108: 73599 | B108: M169 | C108: 23S-078 | D108: PCM(24HRS) | E108: 25-01-652 | F108: 6 | G108: 6 | H108: =F108*G108 -> 36
A109: 73599 | B109: M169 | C109: 23S-078 | D109: PCM(24HRS) | E109: 25-01-660 | F109: 18 | G109: 6 | H109: =F109*G109 -> 108
A110: 73599 | B110: M169 | C110: 23S-078 | D110: PCM(24HRS) | E110: 25-01-677 | F110: 9 | G110: 6 | H110: =F110*G110 -> 54
A111: 73599 | B111: M169 | C111: 23S-078 | D111: PCM(24HRS) | E111: 25-01-721 | F111: 9 | G111: 6 | H111: =F111*G111 -> 54
A112: 73599 | B112: M169 | C112: 23S-078 | D112: PCM(24HRS) | E112: 25-02-077 | F112: 9 | G112: 6 | H112: =F112*G112 -> 54
A113: 75271 | B113: M169 | C113: 23S-078 | D113: TEM-AIR | E113: 25-04-125 | F113: 5 | G113: 50 | H113: =F113*G113 -> 250
A114: 75271 | B114: M169 | C114: 23S-078 | D114: TEM-AIR | E114: 25-04-131 | F114: 5 | G114: 50 | H114: =F114*G114 -> 250
A115: 75481 | B115: M169 | C115: 23S-078 | D115: PCM(24HRS) | E115: 25-04-944 | F115: 12 | G115: 6 | H115: =F115*G115 -> 72
A116: 75481 | B116: M169 | C116: 23S-078 | D116: PCM(24HRS) | E116: 25-04-945 | F116: 6 | G116: 6 | H116: =F116*G116 -> 36
... A153: 66829 | B153: K335 | C153: 23S-075 | D153: PCM(24HRS) | E153: 23-12-842 | F153: 12 | G153: 6 | H153: =F153*G153 -> 72
